setup.py
Products/__init__.py
Products.ParsedXML.egg-info/PKG-INFO
Products.ParsedXML.egg-info/SOURCES.txt
Products.ParsedXML.egg-info/dependency_links.txt
Products.ParsedXML.egg-info/namespace_packages.txt
Products.ParsedXML.egg-info/not-zip-safe
Products.ParsedXML.egg-info/requires.txt
Products.ParsedXML.egg-info/top_level.txt
Products/ParsedXML/AdaptableStorage.py
Products/ParsedXML/CHANGES.txt
Products/ParsedXML/CREDITS.txt
Products/ParsedXML/DOMProxy.py
Products/ParsedXML/Example.zexp
Products/ParsedXML/ExtraDOM.py
Products/ParsedXML/INSTALL.txt
Products/ParsedXML/LICENSE.Fourthought
Products/ParsedXML/LICENSE.txt
Products/ParsedXML/ManageableDOM.py
Products/ParsedXML/ParsedXML.py
Products/ParsedXML/PrettyPrinter.py
Products/ParsedXML/README.DOMProxy
Products/ParsedXML/README.parseprint
Products/ParsedXML/README.txt
Products/ParsedXML/TransPubDOMProxy.py
Products/ParsedXML/__init__.py
Products/ParsedXML/helpers.py
Products/ParsedXML/version.txt
Products/ParsedXML/DOM/Core.py
Products/ParsedXML/DOM/Exceptions.py
Products/ParsedXML/DOM/ExpatBuilder.py
Products/ParsedXML/DOM/LoadSave.py
Products/ParsedXML/DOM/SAXBuilder.py
Products/ParsedXML/DOM/Traversal.py
Products/ParsedXML/DOM/XMLExtended.py
Products/ParsedXML/DOM/__init__.py
Products/ParsedXML/NodePath/ElementIdPath.py
Products/ParsedXML/NodePath/NodePath.py
Products/ParsedXML/NodePath/README.txt
Products/ParsedXML/NodePath/RobustPath.py
Products/ParsedXML/NodePath/__init__.py
Products/ParsedXML/NodePath/tests/test_nodepath.py
Products/ParsedXML/dtml/DOMTree.dtml
Products/ParsedXML/dtml/documentAdd.dtml
Products/ParsedXML/dtml/persEdit.dtml
Products/ParsedXML/dtml/transEdit.dtml
Products/ParsedXML/help/Core.py
Products/ParsedXML/help/ExpatBuilder.py
Products/ParsedXML/help/ExtraDOM.py
Products/ParsedXML/help/ManageableDOM.py
Products/ParsedXML/help/ParsedXML
Products/ParsedXML/help/ParsedXML.stx
Products/ParsedXML/help/ParsedXML_DOM.stx
Products/ParsedXML/help/ParsedXML_Edit.stx
Products/ParsedXML/help/ParsedXML_Raw.stx
Products/ParsedXML/help/ParsedXML_Security.stx
Products/ParsedXML/help/ParsedXML_URLTraversal.stx
Products/ParsedXML/help/ParsedXML_Upload.stx
Products/ParsedXML/help/Printer.py
Products/ParsedXML/help/Traversal.py
Products/ParsedXML/help/XMLExtended.py
Products/ParsedXML/tests/README
