Metadata-Version: 1.0
Name: Products.ParsedXML
Version: 1.5.1
Summary: Parsed XML allows you to use XML objects in the Zope 2 environment.
Home-page: http://www.zope.org/Members/faassen/ParsedXML
Author: Zope community, and various others contributors
Author-email: info@infrae.com
License: ZPL 2.0 and Fourthought license
Keywords: parsedxml xml zope2
Platform: UNKNOWN
Classifier: Framework :: Zope2
Classifier: License :: OSI Approved :: Zope Public License
Classifier: Programming Language :: Python
Classifier: Topic :: Software Development :: Libraries :: Python Modules
Classifier: Topic :: Text Processing :: Markup :: XML
